{
    "label": "Hoe werken de betalingsherinneringen?",
    "position": 31,
    "link": {
      "type": "generated-index",
    "description": "Met onze software kun je eenvoudig, met enkele klikken, al je rappels uitsturen. Je kan dit bovendien doen op verschillende niveaus: bijvoorbeeld eerst braaf, de tweede keer iets dwingender, de derde keer met een extra kost eraan verbonden, de vierde keer met vermelding van incasso. Ons systeem houdt bij welke openstaande facturen vervallen zijn, en welke rappels je al uitgestuurd hebt voor welke factuur."
      }
  }
  